caighdean/__init__.py
caighdean/exceptions.py
caighdean/translator.py
caighdean-0.0.4.dist-info/LICENSE
caighdean-0.0.4.dist-info/METADATA
caighdean-0.0.4.dist-info/WHEEL
caighdean-0.0.4.dist-info/top_level.txt
caighdean-0.0.4.dist-info/RECORD
