Metadata-Version: 2.1
Name: caighdean
Version: 0.0.4
Summary: Python Caighdean
Home-page: https://github.com/translate/python-caighdean
Author: Ryan Northey
Author-email: ryan@synca.io
License: GPL3
Keywords: python caighdean
Platform: UNKNOWN
Classifier: Development Status :: 4 - Beta
Classifier: Intended Audience :: Developers
Classifier: Topic :: Software Development :: Build Tools
Classifier: License :: OSI Approved :: GNU General Public License v3 or later (GPLv3+)
Classifier: Programming Language :: Python :: 2.7
Requires-Dist: requests
Requires-Dist: sacremoses
Provides-Extra: test
Requires-Dist: pytest ; extra == 'test'
Requires-Dist: pytest-mock ; extra == 'test'
Requires-Dist: requests-mock ; extra == 'test'
Requires-Dist: coverage ; extra == 'test'
Requires-Dist: pytest-cov (<2.6) ; extra == 'test'
Requires-Dist: codecov ; extra == 'test'
Requires-Dist: flake8 ; extra == 'test'
